ekzexport/__init__.py
ekzexport/apitypes.py
ekzexport/cli.py
ekzexport/session.py
ekzexport/timeutil.py
ekzexport/util.py
ekzexport/exporters/__init__.py
ekzexport/exporters/csv.py
ekzexport/exporters/influxdb.py
ekzexport-0.2.0.dist-info/METADATA
ekzexport-0.2.0.dist-info/WHEEL
ekzexport-0.2.0.dist-info/entry_points.txt
ekzexport-0.2.0.dist-info/licenses/LICENSE
ekzexport-0.2.0.dist-info/RECORD
