Metadata-Version: 2.4
Name: ekzexport
Version: 0.2.0
Summary: CLI and data exporter for the myEKZ customer portal.
Project-URL: Homepage, https://github.com/mensi/ekzexport
Author-email: Manuel Stocker <mensi@mensi.ch>
License-Expression: Apache-2.0
License-File: LICENSE
Classifier: License :: OSI Approved :: Apache Software License
Classifier: Natural Language :: English
Classifier: Operating System :: OS Independent
Classifier: Programming Language :: Python
Classifier: Programming Language :: Python :: 3 :: Only
Classifier: Programming Language :: Python :: 3.10
Classifier: Programming Language :: Python :: 3.11
Classifier: Programming Language :: Python :: 3.12
Requires-Python: >=3.10
Requires-Dist: beautifulsoup4
Requires-Dist: click
Requires-Dist: platformdirs
Requires-Dist: pyotp
Requires-Dist: requests
Requires-Dist: rich
Requires-Dist: tzdata
Provides-Extra: influx
Requires-Dist: influxdb-client; extra == 'influx'
